MANIFEST.in
README.txt
setup.py
medialog/.DS_Store
medialog/__init__.py
medialog.mobilethemeTwo.egg-info/PKG-INFO
medialog.mobilethemeTwo.egg-info/SOURCES.txt
medialog.mobilethemeTwo.egg-info/dependency_links.txt
medialog.mobilethemeTwo.egg-info/entry_points.txt
medialog.mobilethemeTwo.egg-info/namespace_packages.txt
medialog.mobilethemeTwo.egg-info/not-zip-safe
medialog.mobilethemeTwo.egg-info/requires.txt
medialog.mobilethemeTwo.egg-info/top_level.txt
medialog/mobilethemeTwo/.DS_Store
medialog/mobilethemeTwo/__init__.py
medialog/mobilethemeTwo/configure.zcml
medialog/mobilethemeTwo/interfaces.py
medialog/mobilethemeTwo/views.py
medialog/mobilethemeTwo/profiles/.DS_Store
medialog/mobilethemeTwo/profiles/default/.DS_Store
medialog/mobilethemeTwo/profiles/default/metadata.xml
medialog/mobilethemeTwo/profiles/default/theme.xml
medialog/mobilethemeTwo/static/.DS_Store
medialog/mobilethemeTwo/static/index.html
medialog/mobilethemeTwo/static/manifest.cfg
medialog/mobilethemeTwo/static/offline.html
medialog/mobilethemeTwo/static/rules.xml
medialog/mobilethemeTwo/static/theme.html
medialog/mobilethemeTwo/static/assets/.DS_Store
medialog/mobilethemeTwo/static/assets/addtohomescreen.min.js
medialog/mobilethemeTwo/static/assets/authoring.css
medialog/mobilethemeTwo/static/assets/invisibles.css
medialog/mobilethemeTwo/static/assets/mobiletwo.css
medialog/mobilethemeTwo/static/assets/navigation.css
medialog/mobilethemeTwo/static/assets/ploneui.css
medialog/mobilethemeTwo/static/assets/reset.css
medialog/mobilethemeTwo/static/assets/slider.min.js
medialog/mobilethemeTwo/static/assets/IcoMoon/.DS_Store
medialog/mobilethemeTwo/static/assets/IcoMoon/.gitignore
medialog/mobilethemeTwo/static/assets/IcoMoon/License.txt
medialog/mobilethemeTwo/static/assets/IcoMoon/README
medialog/mobilethemeTwo/static/assets/IcoMoon/Icons/.DS_Store
medialog/mobilethemeTwo/static/assets/IcoMoon/Icons/png/.DS_Store
medialog/mobilethemeTwo/static/assets/IcoMoon/Icons/png/16px/accessibility.png
medialog/mobilethemeTwo/static/assets/IcoMoon/Icons/png/16px/address-book.png
medialog/mobilethemeTwo/static/assets/IcoMoon/Icons/png/16px/aid.png
medialog/mobilethemeTwo/static/assets/IcoMoon/Icons/png/16px/airplane.png
medialog/mobilethemeTwo/static/assets/IcoMoon/Icons/png/16px/alarm.png
medialog/mobilethemeTwo/static/assets/IcoMoon/Icons/png/16px/alarm2.png
