Metadata-Version: 1.1
Name: medialog.mobilethemeTwo
Version: 0.7.1.1
Summary: A diazo theme for zettwerk.mobiletheming
Home-page: http://github.com/espenmn/medialog.mobilethemeTwo
Author: Espen Moe-Nilssen
Author-email: espen@medialog.no
License: gpl
Keywords: mobiletheming plone zetterk
Platform: UNKNOWN
Classifier: Programming Language :: Python
